peritype/__init__.py
peritype/_fwrap.py
peritype/_mapping.py
peritype/_twrap.py
peritype/_wrap.py
peritype/collections/__init__.py
peritype/collections/_bag.py
peritype/collections/_map.py
peritype/collections/_tree.py
peritype/errors.py
peritype/py.typed
peritype/utils/__init__.py
peritype/utils/_cache.py
peritype/utils/_generics.py
peritype/utils/_typing.py
peritype-0.6.0.dist-info/WHEEL
peritype-0.6.0.dist-info/METADATA
peritype-0.6.0.dist-info/RECORD
