Metadata-Version: 2.3
Name: peritype
Version: 0.6.0
Summary: Peritype helps you explore Python types at runtime with ease.
Requires-Python: >=3.13
